tetris
venv
